{"err":0,"errmsg":null,"data":{"nextResupply":1640977140,"items":[{"_id":"61c6dc2cd90a3c717247a486","_tpl":"5aaa5e60e5b5b000140293d6","parentId":"hideout","slotId":"hideout","upd":{"BuyRestrictionMax":8,"BuyRestrictionCurrent":0,"StackObjectsCount":2986}},{"_id":"61c6dc2cd90a3c717247a489","_tpl":"57d17c5e2459775a5c57d17d","parentId":"hideout","slotId":"hideout","upd":{"BuyRestrictionMax":5,"BuyRestrictionCurrent":0,"StackObjectsCount":14992}},{"_id":"61c6dc2dd90a3c717247a4cf","_tpl":"5648ac824bdc2ded0b8b457d","parentId":"hideout","slotId":"hideout","upd":{"BuyRestrictionMax":6,"BuyRestrictionCurrent":0,"StackObjectsCount":149016}},{"_id":"61c6dc2dd90a3c717247a511","_tpl":"58820d1224597753c90aeb13","parentId":"hideout","slotId":"hideout","upd":{"UnlimitedCount":true,"StackObjectsCount":820000}},{"_id":"61c6dc2dd90a3c717247a51c","_tpl":"5a0abb6e1526d8000a025282","parentId":"hideout","slotId":"hideout","upd":{"BuyRestrictionMax":3,"BuyRestrictionCurrent":0,"StackObjectsCount":4967}},{"_id":"61c6dc2dd90a3c717247a51f","_tpl":"59e6152586f77473dc057aa1","parentId":"hideout","slotId":"hideout","location":null,"upd":{"StackObjectsCount":19995}},{"_id":"61c6dc2dd90a3c717247a520","_tpl":"59e649f986f77411d949b246","parentId":"61c6dc2dd90a3c717247a51f","slotId":"mod_gas_block","location":null},{"_id":"61c6dc2dd90a3c717247a521","_tpl":"59e6284f86f77440d569536f","parentId":"61c6dc2dd90a3c717247a520","slotId":"mod_handguard","location":null},{"_id":"61c6dc2dd90a3c717247a522","_tpl":"59e61eb386f77440d64f5daf","parentId":"61c6dc2dd90a3c717247a51f","slotId":"mod_muzzle","location":null},{"_id":"61c6dc2dd90a3c717247a523","_tpl":"59e6318286f77444dd62c4cc","parentId":"61c6dc2dd90a3c717247a51f","slotId":"mod_pistol_grip","location":null},{"_id":"61c6dc2dd90a3c717247a524","_tpl":"59e6449086f7746c9f75e822","parentId":"61c6dc2dd90a3c717247a51f","slotId":"mod_reciever","location":null},{"_id":"61c6dc2dd90a3c717247a525","_tpl":"59d650cf86f7741b846413a4","parentId":"61c6dc2dd90a3c717247a51f","slotId":"mod_sight_rear","location":null},{"_id":"61c6dc2dd90a3c717247a526","_tpl":"59e6227d86f77440d64f5dc2","parentId":"61c6dc2dd90a3c717247a51f","slotId":"mod_stock","location":null},{"_id":"61c6dc2dd90a3c717247a527","_tpl":"59d625f086f774661516605d","parentId":"61c6dc2dd90a3c717247a51f","slotId":"mod_magazine","location":null},{"_id":"61c6dc2dd90a3c717247a529","_tpl":"5c07c60e0db834002330051f","parentId":"hideout","slotId":"hideout","location":null,"upd":{"FireMode":{"FireMode":"single"},"BuyRestrictionMax":4,"BuyRestrictionCurrent":0,"StackObjectsCount":19949}},{"_id":"61c6dc2dd90a3c717247a52a","_tpl":"5c0e2ff6d174af02a1659d4a","parentId":"61c6dc2dd90a3c717247a529","slotId":"mod_pistol_grip","location":null},{"_id":"61c6dc2dd90a3c717247a52b","_tpl":"5aaa5e60e5b5b000140293d6","parentId":"61c6dc2dd90a3c717247a529","slotId":"mod_magazine","location":null},{"_id":"61c6dc2dd90a3c717247a52c","_tpl":"5c0e2f26d174af02a9625114","parentId":"61c6dc2dd90a3c717247a529","slotId":"mod_reciever","location":null},{"_id":"61c6dc2dd90a3c717247a52d","_tpl":"5c0e2f94d174af029f650d56","parentId":"61c6dc2dd90a3c717247a52c","slotId":"mod_barrel","location":null},{"_id":"61c6dc2dd90a3c717247a52e","_tpl":"5c0fafb6d174af02a96260ba","parentId":"61c6dc2dd90a3c717247a52d","slotId":"mod_muzzle","location":null},{"_id":"61c6dc2dd90a3c717247a52f","_tpl":"5ae30e795acfc408fb139a0b","parentId":"61c6dc2dd90a3c717247a52d","slotId":"mod_gas_block","location":null},{"_id":"61c6dc2dd90a3c717247a530","_tpl":"5c0e2f5cd174af02a012cfc9","parentId":"61c6dc2dd90a3c717247a52c","slotId":"mod_handguard","location":null},{"_id":"61c6dc2dd90a3c717247a531","_tpl":"5c0faeddd174af02a962601f","parentId":"61c6dc2dd90a3c717247a529","slotId":"mod_stock","location":null},{"_id":"61c6dc2dd90a3c717247a532","_tpl":"5c0faf68d174af02a96260b8","parentId":"61c6dc2dd90a3c717247a529","slotId":"mod_charge","location":null},{"_id":"61c6dc2dd90a3c717247a543","_tpl":"59e6920f86f77411d82aa167","parentId":"hideout","slotId":"hideout","upd":{"UnlimitedCount":true,"StackObjectsCount":820000}},{"_id":"61c6dc2dd90a3c717247a5a5","_tpl":"5a9fbb74a2750c0032157181","parentId":"hideout","slotId":"hideout","upd":{"BuyRestrictionMax":3,"BuyRestrictionCurrent":0,"StackObjectsCount":3949}},{"_id":"61c6dc2dd90a3c717247a5ab","_tpl":"57ade1442459771557167e15","parentId":"hideout","slotId":"hideout","upd":{"BuyRestrictionMax":5,"BuyRestrictionCurrent":0,"StackObjectsCount":14997}},{"_id":"61c6dc2dd90a3c717247a5cf","_tpl":"59ccfdba86f7747f2109a587","parentId":"hideout","slotId":"hideout","upd":{"BuyRestrictionMax":6,"BuyRestrictionCurrent":0,"StackObjectsCount":24969}},{"_id":"61c6dc2dd90a3c717247a5d5","_tpl":"5f2aa43ba9b91d26f20ae6d2","parentId":"hideout","slotId":"hideout","upd":{"BuyRestrictionMax":7,"BuyRestrictionCurrent":0,"StackObjectsCount":19962}},{"_id":"61c6dc2dd90a3c717247a601","_tpl":"57ffa9f4245977728561e844","parentId":"hideout","slotId":"hideout","upd":{"BuyRestrictionMax":4,"BuyRestrictionCurrent":0,"StackObjectsCount":14859}},{"_id":"61c6dc2ed90a3c717247a60a","_tpl":"5c1bc7752e221602b1779b34","parentId":"hideout","slotId":"hideout","upd":{"BuyRestrictionMax":5,"BuyRestrictionCurrent":0,"StackObjectsCount":19804}},{"_id":"61c6dc2ed90a3c717247a616","_tpl":"57d17e212459775a1179a0f5","parentId":"hideout","slotId":"hideout","upd":{"BuyRestrictionMax":5,"BuyRestrictionCurrent":0,"StackObjectsCount":14993}},{"_id":"61c6dc2ed90a3c717247a636","_tpl":"59e6449086f7746c9f75e822","parentId":"hideout","slotId":"hideout","upd":{"BuyRestrictionMax":10,"BuyRestrictionCurrent":0,"StackObjectsCount":19990}},{"_id":"61c6dc2ed90a3c717247a64a","_tpl":"5b1fd4e35acfc40018633c39","parentId":"hideout","slotId":"hideout","upd":{"UnlimitedCount":true,"StackObjectsCount":820000}},{"_id":"61c6dc2ed90a3c717247a653","_tpl":"59e6152586f77473dc057aa1","parentId":"hideout","slotId":"hideout","location":null,"upd":{"BuyRestrictionMax":5,"BuyRestrictionCurrent":0,"StackObjectsCount":149911}},{"_id":"61c6dc2ed90a3c717247a654","_tpl":"59e649f986f77411d949b246","parentId":"61c6dc2ed90a3c717247a653","slotId":"mod_gas_block","location":null},{"_id":"61c6dc2ed90a3c717247a655","_tpl":"59e6284f86f77440d569536f","parentId":"61c6dc2ed90a3c717247a654","slotId":"mod_handguard","location":null},{"_id":"61c6dc2ed90a3c717247a656","_tpl":"59e61eb386f77440d64f5daf","parentId":"61c6dc2ed90a3c717247a653","slotId":"mod_muzzle","location":null},{"_id":"61c6dc2ed90a3c717247a657","_tpl":"59e6318286f77444dd62c4cc","parentId":"61c6dc2ed90a3c717247a653","slotId":"mod_pistol_grip","location":null},{"_id":"61c6dc2ed90a3c717247a658","_tpl":"59e6449086f7746c9f75e822","parentId":"61c6dc2ed90a3c717247a653","slotId":"mod_reciever","location":null},{"_id":"61c6dc2ed90a3c717247a659","_tpl":"59d650cf86f7741b846413a4","parentId":"61c6dc2ed90a3c717247a653","slotId":"mod_sight_rear","location":null},{"_id":"61c6dc2ed90a3c717247a65a","_tpl":"59e6227d86f77440d64f5dc2","parentId":"61c6dc2ed90a3c717247a653","slotId":"mod_stock","location":null},{"_id":"61c6dc2ed90a3c717247a65b","_tpl":"59d625f086f774661516605d","parentId":"61c6dc2ed90a3c717247a653","slotId":"mod_magazine","location":null},{"_id":"61c6dc2ed90a3c717247a665","_tpl":"5998529a86f774647f44f421","parentId":"hideout","slotId":"hideout","upd":{"BuyRestrictionMax":6,"BuyRestrictionCurrent":0,"StackObjectsCount":14970}},{"_id":"61c6dc2ed90a3c717247a667","_tpl":"59e5d83b86f7745aed03d262","parentId":"hideout","slotId":"hideout","upd":{"UnlimitedCount":true,"StackObjectsCount":820000}},{"_id":"61c6dc2ed90a3c717247a679","_tpl":"560d5e524bdc2d25448b4571","parentId":"hideout","slotId":"hideout","upd":{"UnlimitedCount":true,"StackObjectsCount":820000}},{"_id":"61c6dc2ed90a3c717247a67c","_tpl":"570fd721d2720bc5458b4596","parentId":"hideout","slotId":"hideout","upd":{"BuyRestrictionMax":3,"BuyRestrictionCurrent":0,"StackObjectsCount":14752}},{"_id":"61c6dc2ed90a3c717247a68a","_tpl":"5bfe7fb30db8340018089fed","parentId":"hideout","slotId":"hideout","upd":{"BuyRestrictionMax":5,"BuyRestrictionCurrent":0,"StackObjectsCount":2977}},{"_id":"61c6dc2ed90a3c717247a69b","_tpl":"59e6284f86f77440d569536f","parentId":"hideout","slotId":"hideout","upd":{"BuyRestrictionMax":10,"BuyRestrictionCurrent":0,"StackObjectsCount":19997}},{"_id":"61c6dc2ed90a3c717247a6a2","_tpl":"5c0673fb0db8340023300271","parentId":"hideout","slotId":"hideout","upd":{"StackObjectsCount":4969}},{"_id":"61c6dc2ed90a3c717247a6a5","_tpl":"59e6227d86f77440d64f5dc2","parentId":"hideout","slotId":"hideout","upd":{"BuyRestrictionMax":10,"BuyRestrictionCurrent":0,"StackObjectsCount":19993}},{"_id":"61c6dc2ed90a3c717247a6a9","_tpl":"59e6318286f77444dd62c4cc","parentId":"hideout","slotId":"hideout","upd":{"BuyRestrictionMax":10,"BuyRestrictionCurrent":0,"StackObjectsCount":19998}},{"_id":"61c6dc2ed90a3c717247a6c3","_tpl":"5c78f2792e221600106f4683","parentId":"hideout","slotId":"hideout","upd":{"BuyRestrictionMax":5,"BuyRestrictionCurrent":0,"StackObjectsCount":3787}},{"_id":"61c6dc2ed90a3c717247a6d2","_tpl":"5c07c60e0db834002330051f","parentId":"hideout","slotId":"hideout","upd":{"BuyRestrictionMax":3,"BuyRestrictionCurrent":0,"StackObjectsCount":1986}},{"_id":"61c6dc2ed90a3c717247a6e5","_tpl":"59e6542b86f77411dc52a77a","parentId":"hideout","slotId":"hideout","upd":{"UnlimitedCount":true,"StackObjectsCount":820000}},{"_id":"61c6dc2ed90a3c717247a706","_tpl":"5cc9c20cd7f00c001336c65d","parentId":"hideout","slotId":"hideout","upd":{"BuyRestrictionMax":3,"BuyRestrictionCurrent":0,"StackObjectsCount":18589}},{"_id":"61c6dc2ed90a3c717247a71a","_tpl":"57616a9e2459773c7a400234","parentId":"hideout","slotId":"hideout","upd":{"StackObjectsCount":199980}},{"_id":"61c6dc2ed90a3c717247a726","_tpl":"5d2c76ed48f03532f2136169","parentId":"hideout","slotId":"hideout","upd":{"BuyRestrictionMax":5,"BuyRestrictionCurrent":0,"StackObjectsCount":19476}},{"_id":"61c6dc2fd90a3c717247a744","_tpl":"5c0faeddd174af02a962601f","parentId":"hideout","slotId":"hideout","upd":{"BuyRestrictionMax":4,"BuyRestrictionCurrent":0,"StackObjectsCount":1990}},{"_id":"61c6dc2fd90a3c717247a749","_tpl":"5a38e6bac4a2826c6e06d79b","parentId":"hideout","slotId":"hideout","location":null,"upd":{"UnlimitedCount":true,"StackObjectsCount":820000}},{"_id":"61c6dc2fd90a3c717247a74a","_tpl":"5a38ee51c4a282000c5a955c","parentId":"61c6dc2fd90a3c717247a749","slotId":"mod_magazine","location":null},{"_id":"61c6dc2fd90a3c717247a74b","_tpl":"5a38ef1fc4a282000b1521f6","parentId":"61c6dc2fd90a3c717247a749","slotId":"mod_stock","location":null},{"_id":"61c6dc2fd90a3c717247a74c","_tpl":"5a38eecdc4a282329a73b512","parentId":"61c6dc2fd90a3c717247a74b","slotId":"mod_pistol_grip","location":null},{"_id":"61c6dc2fd90a3c717247a752","_tpl":"5a38ebd9c4a282000d722a5b","parentId":"hideout","slotId":"hideout","upd":{"UnlimitedCount":true,"StackObjectsCount":820000}},{"_id":"61c6dc2fd90a3c717247a757","_tpl":"5a38ee51c4a282000c5a955c","parentId":"hideout","slotId":"hideout","upd":{"UnlimitedCount":true,"StackObjectsCount":820000}},{"_id":"61c6dc2fd90a3c717247a759","_tpl":"5d2c829448f0353a5c7d6674","parentId":"hideout","slotId":"hideout","upd":{"BuyRestrictionMax":3,"BuyRestrictionCurrent":0,"StackObjectsCount":5945}},{"_id":"61c6dc2fd90a3c717247a7ef","_tpl":"56dee2bdd2720bc8328b4567","parentId":"hideout","slotId":"hideout","location":null,"upd":{"BuyRestrictionMax":2,"BuyRestrictionCurrent":0,"StackObjectsCount":4999}},{"_id":"61c6dc2fd90a3c717247a7f0","_tpl":"56deec93d2720bec348b4568","parentId":"61c6dc2fd90a3c717247a7ef","slotId":"mod_barrel","location":null},{"_id":"61c6dc2fd90a3c717247a7f1","_tpl":"56deed6ed2720b4c698b4583","parentId":"61c6dc2fd90a3c717247a7ef","slotId":"mod_handguard","location":null},{"_id":"61c6dc2fd90a3c717247a7f2","_tpl":"56deee15d2720bee328b4567","parentId":"61c6dc2fd90a3c717247a7ef","slotId":"mod_magazine","location":null},{"_id":"61c6dc2fd90a3c717247a7f3","_tpl":"56083be64bdc2d20478b456f","parentId":"61c6dc2fd90a3c717247a7ef","slotId":"mod_stock","location":null},{"_id":"61c6dc2fd90a3c717247a7fb","_tpl":"5c0e5edb86f77461f55ed1f7","parentId":"hideout","slotId":"hideout","upd":{"BuyRestrictionMax":1,"BuyRestrictionCurrent":0,"StackObjectsCount":2000}},{"_id":"61c6dc2fd90a3c717247a833","_tpl":"6033fa48ffd42c541047f728","parentId":"hideout","slotId":"hideout","upd":{"UnlimitedCount":true,"StackObjectsCount":820000}},{"_id":"61c6dc2fd90a3c717247a841","_tpl":"602e71bd53a60014f9705bfa","parentId":"hideout","slotId":"hideout","upd":{"BuyRestrictionMax":4,"BuyRestrictionCurrent":0,"StackObjectsCount":15980}}],"barter_scheme":{"61c6dc2cd90a3c717247a486":[[{"count":2302,"_tpl":"5449016a4bdc2d6f028b456f"}]],"61c6dc2cd90a3c717247a489":[[{"count":34.78,"_tpl":"569668774bdc2da2298b4568"}]],"61c6dc2dd90a3c717247a4cf":[[{"count":3063,"_tpl":"5449016a4bdc2d6f028b456f"}]],"61c6dc2dd90a3c717247a511":[[{"count":65,"_tpl":"5449016a4bdc2d6f028b456f"}]],"61c6dc2dd90a3c717247a51c":[[{"count":708,"_tpl":"5449016a4bdc2d6f028b456f"}]],"61c6dc2dd90a3c717247a51f":[[{"count":2,"_tpl":"573478bc24597738002c6175"}]],"61c6dc2dd90a3c717247a529":[[{"count":45388,"_tpl":"5449016a4bdc2d6f028b456f"}]],"61c6dc2dd90a3c717247a543":[[{"count":98,"_tpl":"5449016a4bdc2d6f028b456f"}]],"61c6dc2dd90a3c717247a5a5":[[{"count":28784,"_tpl":"5449016a4bdc2d6f028b456f"}]],"61c6dc2dd90a3c717247a5ab":[[{"count":6189,"_tpl":"5449016a4bdc2d6f028b456f"}]],"61c6dc2dd90a3c717247a5cf":[[{"count":2578,"_tpl":"5449016a4bdc2d6f028b456f"}]],"61c6dc2dd90a3c717247a5d5":[[{"count":2530,"_tpl":"5449016a4bdc2d6f028b456f"}]],"61c6dc2dd90a3c717247a601":[[{"count":5974,"_tpl":"5449016a4bdc2d6f028b456f"}]],"61c6dc2ed90a3c717247a60a":[[{"count":7263,"_tpl":"5449016a4bdc2d6f028b456f"}]],"61c6dc2ed90a3c717247a616":[[{"count":3219,"_tpl":"5449016a4bdc2d6f028b456f"}]],"61c6dc2ed90a3c717247a636":[[{"count":1148,"_tpl":"5449016a4bdc2d6f028b456f"}]],"61c6dc2ed90a3c717247a64a":[[{"count":805,"_tpl":"5449016a4bdc2d6f028b456f"}]],"61c6dc2ed90a3c717247a653":[[{"count":32420,"_tpl":"5449016a4bdc2d6f028b456f"}]],"61c6dc2ed90a3c717247a665":[[{"count":1724,"_tpl":"5449016a4bdc2d6f028b456f"}]],"61c6dc2ed90a3c717247a667":[[{"count":1148,"_tpl":"5449016a4bdc2d6f028b456f"}]],"61c6dc2ed90a3c717247a679":[[{"count":35,"_tpl":"5449016a4bdc2d6f028b456f"}]],"61c6dc2ed90a3c717247a67c":[[{"count":13800,"_tpl":"5449016a4bdc2d6f028b456f"}]],"61c6dc2ed90a3c717247a68a":[[{"count":2530,"_tpl":"5449016a4bdc2d6f028b456f"}]],"61c6dc2ed90a3c717247a69b":[[{"count":922,"_tpl":"5449016a4bdc2d6f028b456f"}]],"61c6dc2ed90a3c717247a6a2":[[{"count":2128,"_tpl":"5449016a4bdc2d6f028b456f"}]],"61c6dc2ed90a3c717247a6a5":[[{"count":2098,"_tpl":"5449016a4bdc2d6f028b456f"}]],"61c6dc2ed90a3c717247a6a9":[[{"count":884,"_tpl":"5449016a4bdc2d6f028b456f"}]],"61c6dc2ed90a3c717247a6c3":[[{"count":10120,"_tpl":"5449016a4bdc2d6f028b456f"}]],"61c6dc2ed90a3c717247a6d2":[[{"count":7245,"_tpl":"5449016a4bdc2d6f028b456f"}]],"61c6dc2ed90a3c717247a6e5":[[{"count":51,"_tpl":"5449016a4bdc2d6f028b456f"}]],"61c6dc2ed90a3c717247a706":[[{"count":5658,"_tpl":"5449016a4bdc2d6f028b456f"}]],"61c6dc2ed90a3c717247a71a":[[{"count":1949,"_tpl":"5449016a4bdc2d6f028b456f"}]],"61c6dc2ed90a3c717247a726":[[{"count":6325,"_tpl":"5449016a4bdc2d6f028b456f"}]],"61c6dc2fd90a3c717247a744":[[{"count":920,"_tpl":"5449016a4bdc2d6f028b456f"}]],"61c6dc2fd90a3c717247a749":[[{"count":8917,"_tpl":"5449016a4bdc2d6f028b456f"}]],"61c6dc2fd90a3c717247a752":[[{"count":28,"_tpl":"5449016a4bdc2d6f028b456f"}]],"61c6dc2fd90a3c717247a757":[[{"count":903,"_tpl":"5449016a4bdc2d6f028b456f"}]],"61c6dc2fd90a3c717247a759":[[{"count":3968,"_tpl":"5449016a4bdc2d6f028b456f"}]],"61c6dc2fd90a3c717247a7ef":[[{"count":1,"_tpl":"591ae8f986f77406f854be45"},{"count":1,"_tpl":"59136f6f86f774447a1ed173"},{"count":1,"_tpl":"5913651986f774432f15d132"}]],"61c6dc2fd90a3c717247a7fb":[[{"count":1,"_tpl":"59e3658a86f7741776641ac4"},{"count":1,"_tpl":"5b4329075acfc400153b78ff"}]],"61c6dc2fd90a3c717247a833":[[{"count":19550,"_tpl":"5449016a4bdc2d6f028b456f"}]],"61c6dc2fd90a3c717247a841":[[{"count":1898,"_tpl":"5449016a4bdc2d6f028b456f"}]]},"loyal_level_items":{"61c6dc2cd90a3c717247a46e":3,"61c6dc2cd90a3c717247a471":3,"61c6dc2cd90a3c717247a474":3,"61c6dc2cd90a3c717247a477":2,"61c6dc2cd90a3c717247a47a":2,"61c6dc2cd90a3c717247a47d":2,"61c6dc2cd90a3c717247a480":2,"61c6dc2cd90a3c717247a483":4,"61c6dc2cd90a3c717247a486":1,"61c6dc2cd90a3c717247a489":1,"61c6dc2cd90a3c717247a48c":3,"61c6dc2cd90a3c717247a48f":3,"61c6dc2dd90a3c717247a492":3,"61c6dc2dd90a3c717247a495":3,"61c6dc2dd90a3c717247a498":3,"61c6dc2dd90a3c717247a49b":1,"61c6dc2dd90a3c717247a4ae":1,"61c6dc2dd90a3c717247a4b1":3,"61c6dc2dd90a3c717247a4c0":4,"61c6dc2dd90a3c717247a4c3":4,"61c6dc2dd90a3c717247a4c5":2,"61c6dc2dd90a3c717247a4c8":4,"61c6dc2dd90a3c717247a4ca":2,"61c6dc2dd90a3c717247a4cc":2,"61c6dc2dd90a3c717247a4cf":1,"61c6dc2dd90a3c717247a4d2":2,"61c6dc2dd90a3c717247a4d5":3,"61c6dc2dd90a3c717247a4d8":3,"61c6dc2dd90a3c717247a4db":3,"61c6dc2dd90a3c717247a4de":2,"61c6dc2dd90a3c717247a4e1":2,"61c6dc2dd90a3c717247a4e4":2,"61c6dc2dd90a3c717247a4e7":2,"61c6dc2dd90a3c717247a4ea":4,"61c6dc2dd90a3c717247a4ed":1,"61c6dc2dd90a3c717247a500":2,"61c6dc2dd90a3c717247a503":4,"61c6dc2dd90a3c717247a50b":3,"61c6dc2dd90a3c717247a50e":3,"61c6dc2dd90a3c717247a511":1,"61c6dc2dd90a3c717247a514":3,"61c6dc2dd90a3c717247a516":2,"61c6dc2dd90a3c717247a519":2,"61c6dc2dd90a3c717247a51c":1,"61c6dc2dd90a3c717247a51f":1,"61c6dc2dd90a3c717247a529":1,"61c6dc2dd90a3c717247a53d":3,"61c6dc2dd90a3c717247a540":2,"61c6dc2dd90a3c717247a543":1,"61c6dc2dd90a3c717247a546":3,"61c6dc2dd90a3c717247a549":4,"61c6dc2dd90a3c717247a54b":3,"61c6dc2dd90a3c717247a54e":3,"61c6dc2dd90a3c717247a551":3,"61c6dc2dd90a3c717247a554":4,"61c6dc2dd90a3c717247a557":2,"61c6dc2dd90a3c717247a55a":3,"61c6dc2dd90a3c717247a55d":2,"61c6dc2dd90a3c717247a560":2,"61c6dc2dd90a3c717247a56f":3,"61c6dc2dd90a3c717247a58a":3,"61c6dc2dd90a3c717247a58d":3,"61c6dc2dd90a3c717247a58f":3,"61c6dc2dd90a3c717247a591":4,"61c6dc2dd90a3c717247a5a5":1,"61c6dc2dd90a3c717247a5a8":3,"61c6dc2dd90a3c717247a5ab":1,"61c6dc2dd90a3c717247a5ae":4,"61c6dc2dd90a3c717247a5c9":2,"61c6dc2dd90a3c717247a5cc":4,"61c6dc2dd90a3c717247a5cf":1,"61c6dc2dd90a3c717247a5d2":4,"61c6dc2dd90a3c717247a5d5":1,"61c6dc2dd90a3c717247a5d8":2,"61c6dc2dd90a3c717247a5db":3,"61c6dc2dd90a3c717247a5de":3,"61c6dc2dd90a3c717247a5e1":3,"61c6dc2dd90a3c717247a5e4":3,"61c6dc2dd90a3c717247a5e7":2,"61c6dc2dd90a3c717247a5ea":3,"61c6dc2dd90a3c717247a5ed":2,"61c6dc2dd90a3c717247a5f8":3,"61c6dc2dd90a3c717247a5fb":3,"61c6dc2dd90a3c717247a5fe":4,"61c6dc2dd90a3c717247a601":1,"61c6dc2dd90a3c717247a604":3,"61c6dc2dd90a3c717247a607":3,"61c6dc2ed90a3c717247a60a":1,"61c6dc2ed90a3c717247a60d":4,"61c6dc2ed90a3c717247a610":4,"61c6dc2ed90a3c717247a613":2,"61c6dc2ed90a3c717247a616":1,"61c6dc2ed90a3c717247a619":3,"61c6dc2ed90a3c717247a61c":3,"61c6dc2ed90a3c717247a61f":2,"61c6dc2ed90a3c717247a622":2,"61c6dc2ed90a3c717247a625":3,"61c6dc2ed90a3c717247a628":4,"61c6dc2ed90a3c717247a62b":4,"61c6dc2ed90a3c717247a62e":2,"61c6dc2ed90a3c717247a631":3,"61c6dc2ed90a3c717247a633":2,"61c6dc2ed90a3c717247a636":1,"61c6dc2ed90a3c717247a638":4,"61c6dc2ed90a3c717247a63b":2,"61c6dc2ed90a3c717247a63e":2,"61c6dc2ed90a3c717247a641":2,"61c6dc2ed90a3c717247a644":4,"61c6dc2ed90a3c717247a647":3,"61c6dc2ed90a3c717247a64a":1,"61c6dc2ed90a3c717247a64d":4,"61c6dc2ed90a3c717247a650":3,"61c6dc2ed90a3c717247a653":1,"61c6dc2ed90a3c717247a662":3,"61c6dc2ed90a3c717247a665":1,"61c6dc2ed90a3c717247a667":1,"61c6dc2ed90a3c717247a66a":2,"61c6dc2ed90a3c717247a66d":4,"61c6dc2ed90a3c717247a670":3,"61c6dc2ed90a3c717247a673":2,"61c6dc2ed90a3c717247a676":2,"61c6dc2ed90a3c717247a679":1,"61c6dc2ed90a3c717247a67c":1,"61c6dc2ed90a3c717247a67f":3,"61c6dc2ed90a3c717247a682":2,"61c6dc2ed90a3c717247a685":4,"61c6dc2ed90a3c717247a687":2,"61c6dc2ed90a3c717247a68a":1,"61c6dc2ed90a3c717247a68d":3,"61c6dc2ed90a3c717247a690":3,"61c6dc2ed90a3c717247a692":2,"61c6dc2ed90a3c717247a695":4,"61c6dc2ed90a3c717247a698":2,"61c6dc2ed90a3c717247a69b":1,"61c6dc2ed90a3c717247a69d":2,"61c6dc2ed90a3c717247a69f":2,"61c6dc2ed90a3c717247a6a2":1,"61c6dc2ed90a3c717247a6a5":1,"61c6dc2ed90a3c717247a6a7":2,"61c6dc2ed90a3c717247a6a9":1,"61c6dc2ed90a3c717247a6ab":3,"61c6dc2ed90a3c717247a6ae":4,"61c6dc2ed90a3c717247a6b1":2,"61c6dc2ed90a3c717247a6b4":3,"61c6dc2ed90a3c717247a6b7":3,"61c6dc2ed90a3c717247a6ba":2,"61c6dc2ed90a3c717247a6bd":2,"61c6dc2ed90a3c717247a6c0":4,"61c6dc2ed90a3c717247a6c3":1,"61c6dc2ed90a3c717247a6c6":4,"61c6dc2ed90a3c717247a6c9":2,"61c6dc2ed90a3c717247a6cc":4,"61c6dc2ed90a3c717247a6cf":2,"61c6dc2ed90a3c717247a6d2":1,"61c6dc2ed90a3c717247a6d4":3,"61c6dc2ed90a3c717247a6dc":4,"61c6dc2ed90a3c717247a6df":4,"61c6dc2ed90a3c717247a6e2":4,"61c6dc2ed90a3c717247a6e5":1,"61c6dc2ed90a3c717247a6e8":4,"61c6dc2ed90a3c717247a6eb":3,"61c6dc2ed90a3c717247a6ee":3,"61c6dc2ed90a3c717247a6f1":4,"61c6dc2ed90a3c717247a6f4":3,"61c6dc2ed90a3c717247a6f7":2,"61c6dc2ed90a3c717247a6fa":3,"61c6dc2ed90a3c717247a6fd":3,"61c6dc2ed90a3c717247a700":2,"61c6dc2ed90a3c717247a703":3,"61c6dc2ed90a3c717247a706":1,"61c6dc2ed90a3c717247a709":3,"61c6dc2ed90a3c717247a70c":3,"61c6dc2ed90a3c717247a70f":1,"61c6dc2ed90a3c717247a71a":1,"61c6dc2ed90a3c717247a71d":3,"61c6dc2ed90a3c717247a720":4,"61c6dc2ed90a3c717247a723":3,"61c6dc2ed90a3c717247a726":1,"61c6dc2ed90a3c717247a729":3,"61c6dc2fd90a3c717247a744":1,"61c6dc2fd90a3c717247a746":2,"61c6dc2fd90a3c717247a749":1,"61c6dc2fd90a3c717247a752":1,"61c6dc2fd90a3c717247a755":4,"61c6dc2fd90a3c717247a757":1,"61c6dc2fd90a3c717247a759":1,"61c6dc2fd90a3c717247a75c":4,"61c6dc2fd90a3c717247a75f":3,"61c6dc2fd90a3c717247a761":3,"61c6dc2fd90a3c717247a763":4,"61c6dc2fd90a3c717247a766":3,"61c6dc2fd90a3c717247a768":3,"61c6dc2fd90a3c717247a76b":4,"61c6dc2fd90a3c717247a76e":3,"61c6dc2fd90a3c717247a770":4,"61c6dc2fd90a3c717247a773":4,"61c6dc2fd90a3c717247a776":4,"61c6dc2fd90a3c717247a779":3,"61c6dc2fd90a3c717247a77c":3,"61c6dc2fd90a3c717247a77e":2,"61c6dc2fd90a3c717247a781":3,"61c6dc2fd90a3c717247a784":2,"61c6dc2fd90a3c717247a793":2,"61c6dc2fd90a3c717247a796":2,"61c6dc2fd90a3c717247a799":4,"61c6dc2fd90a3c717247a79c":3,"61c6dc2fd90a3c717247a79e":3,"61c6dc2fd90a3c717247a7a1":2,"61c6dc2fd90a3c717247a7a3":2,"61c6dc2fd90a3c717247a7a5":2,"61c6dc2fd90a3c717247a7a8":2,"61c6dc2fd90a3c717247a7aa":2,"61c6dc2fd90a3c717247a7ac":2,"61c6dc2fd90a3c717247a7ae":2,"61c6dc2fd90a3c717247a7b0":2,"61c6dc2fd90a3c717247a7b3":2,"61c6dc2fd90a3c717247a7b5":3,"61c6dc2fd90a3c717247a7b8":3,"61c6dc2fd90a3c717247a7d3":3,"61c6dc2fd90a3c717247a7d5":3,"61c6dc2fd90a3c717247a7d8":3,"61c6dc2fd90a3c717247a7da":3,"61c6dc2fd90a3c717247a7dd":3,"61c6dc2fd90a3c717247a7df":3,"61c6dc2fd90a3c717247a7e1":3,"61c6dc2fd90a3c717247a7e3":2,"61c6dc2fd90a3c717247a7e5":3,"61c6dc2fd90a3c717247a7e7":3,"61c6dc2fd90a3c717247a7ea":2,"61c6dc2fd90a3c717247a7ed":3,"61c6dc2fd90a3c717247a7ef":1,"61c6dc2fd90a3c717247a7f5":4,"61c6dc2fd90a3c717247a7f7":3,"61c6dc2fd90a3c717247a7f9":2,"61c6dc2fd90a3c717247a7fb":1,"61c6dc2fd90a3c717247a7fd":3,"61c6dc2fd90a3c717247a800":2,"61c6dc2fd90a3c717247a80e":2,"61c6dc2fd90a3c717247a824":3,"61c6dc2fd90a3c717247a827":3,"61c6dc2fd90a3c717247a829":3,"61c6dc2fd90a3c717247a82c":4,"61c6dc2fd90a3c717247a82f":3,"61c6dc2fd90a3c717247a831":3,"61c6dc2fd90a3c717247a833":1,"61c6dc2fd90a3c717247a836":4,"61c6dc2fd90a3c717247a839":3,"61c6dc2fd90a3c717247a83c":2,"61c6dc2fd90a3c717247a83e":4,"61c6dc2fd90a3c717247a841":1,"61c6dc2fd90a3c717247a843":3,"61c6dc2fd90a3c717247a845":3,"61c6dc2fd90a3c717247a847":3,"61c6dc2fd90a3c717247a849":3,"61c6dc2fd90a3c717247a84b":3,"61c6dc2fd90a3c717247a84e":3,"61c6dc2fd90a3c717247a851":3,"61c6dc2fd90a3c717247a854":3}}}