{"err":0,"errmsg":null,"data":{"nextResupply":1644516900,"items":[{"_id":"61fcf31455324313dd16dafa","_tpl":"5b3b6e495acfc4330140bd88","parentId":"hideout","slotId":"hideout","upd":{"StackObjectsCount":1996}},{"_id":"61fcf31455324313dd16dafc","_tpl":"5a6b60158dc32e000a31138b","parentId":"hideout","slotId":"hideout","upd":{"StackObjectsCount":3948}},{"_id":"61fcf31455324313dd16db06","_tpl":"59d36a0086f7747e673f3946","parentId":"hideout","slotId":"hideout","upd":{"BuyRestrictionMax":5,"BuyRestrictionCurrent":0,"StackObjectsCount":11835}},{"_id":"61fcf31455324313dd16db4b","_tpl":"5a7ae0c351dfba0017554310","parentId":"hideout","slotId":"hideout","location":null,"upd":{"UnlimitedCount":true,"StackObjectsCount":760000}},{"_id":"61fcf31455324313dd16db4c","_tpl":"5a6b5f868dc32e000a311389","parentId":"61fcf31455324313dd16db4b","slotId":"mod_barrel","location":null},{"_id":"61fcf31455324313dd16db4d","_tpl":"5a6f5e048dc32e00094b97da","parentId":"61fcf31455324313dd16db4b","slotId":"mod_reciever","location":null},{"_id":"61fcf31455324313dd16db4e","_tpl":"5a6f5d528dc32e00094b97d9","parentId":"61fcf31455324313dd16db4d","slotId":"mod_sight_rear","location":null},{"_id":"61fcf31455324313dd16db4f","_tpl":"5a6f58f68dc32e000a311390","parentId":"61fcf31455324313dd16db4d","slotId":"mod_sight_front","location":null},{"_id":"61fcf31455324313dd16db50","_tpl":"5a718b548dc32e000d46d262","parentId":"61fcf31455324313dd16db4b","slotId":"mod_magazine","location":null},{"_id":"61fcf31455324313dd16db52","_tpl":"56eabcd4d2720b66698b4574","parentId":"hideout","slotId":"hideout","upd":{"BuyRestrictionMax":4,"BuyRestrictionCurrent":0,"StackObjectsCount":11909}},{"_id":"61fcf31455324313dd16db80","_tpl":"5a16bb52fcdbcb001a3b00dc","parentId":"hideout","slotId":"hideout","location":null,"upd":{"StackObjectsCount":1987}},{"_id":"61fcf31455324313dd16db81","_tpl":"5a16b8a9fcdbcb00165aa6ca","parentId":"61fcf31455324313dd16db80","slotId":"mod_nvg","location":null},{"_id":"61fcf31455324313dd16db82","_tpl":"5a16b93dfcdbcbcae6687261","parentId":"61fcf31455324313dd16db81","slotId":"mod_nvg","location":null},{"_id":"61fcf31455324313dd16db83","_tpl":"57235b6f24597759bf5a30f1","parentId":"61fcf31455324313dd16db82","slotId":"mod_nvg","location":null},{"_id":"61fcf31455324313dd16dbab","_tpl":"5a6b5f868dc32e000a311389","parentId":"hideout","slotId":"hideout","upd":{"StackObjectsCount":1916}},{"_id":"61fcf31455324313dd16dbc9","_tpl":"5ba26812d4351e003201fef1","parentId":"hideout","slotId":"hideout","upd":{"UnlimitedCount":true,"StackObjectsCount":585000}},{"_id":"61fcf31455324313dd16dc1a","_tpl":"5b7d6c105acfc40015109a5f","parentId":"hideout","slotId":"hideout","upd":{"StackObjectsCount":1996}},{"_id":"61fcf31455324313dd16dc1c","_tpl":"5a800961159bd4315e3a1657","parentId":"hideout","slotId":"hideout","upd":{"BuyRestrictionMax":4,"BuyRestrictionCurrent":0,"StackObjectsCount":5149}},{"_id":"61fcf31455324313dd16dc34","_tpl":"5ba264f6d4351e0034777d52","parentId":"hideout","slotId":"hideout","upd":{"BuyRestrictionMax":6,"BuyRestrictionCurrent":0,"StackObjectsCount":3514}},{"_id":"61fcf31555324313dd16dc42","_tpl":"57d17e212459775a1179a0f5","parentId":"hideout","slotId":"hideout","upd":{"StackObjectsCount":14925}},{"_id":"61fcf31555324313dd16dc46","_tpl":"59984ab886f7743e98271174","parentId":"hideout","slotId":"hideout","location":null,"upd":{"BuyRestrictionMax":1,"BuyRestrictionCurrent":0,"StackObjectsCount":150}},{"_id":"61fcf31555324313dd16dc47","_tpl":"5649ae4a4bdc2d1b2b8b4588","parentId":"61fcf31555324313dd16dc46","slotId":"mod_pistol_grip","location":null},{"_id":"61fcf31555324313dd16dc48","_tpl":"5ac78eaf5acfc4001926317a","parentId":"61fcf31555324313dd16dc46","slotId":"mod_stock","location":null},{"_id":"61fcf31555324313dd16dc49","_tpl":"59ecc3dd86f7746dc827481c","parentId":"61fcf31555324313dd16dc48","slotId":"mod_stock","location":null},{"_id":"61fcf31555324313dd16dc4a","_tpl":"5648ac824bdc2ded0b8b457d","parentId":"61fcf31555324313dd16dc46","slotId":"mod_charge","location":null},{"_id":"61fcf31555324313dd16dc4b","_tpl":"599860ac86f77436b225ed1a","parentId":"61fcf31555324313dd16dc46","slotId":"mod_magazine","location":null},{"_id":"61fcf31555324313dd16dc4c","_tpl":"59bfc5c886f7743bf6794e62","parentId":"61fcf31555324313dd16dc46","slotId":"mod_muzzle","location":null},{"_id":"61fcf31555324313dd16dc4d","_tpl":"59985a6c86f77414ec448d17","parentId":"61fcf31555324313dd16dc46","slotId":"mod_reciever","location":null},{"_id":"61fcf31555324313dd16dc4e","_tpl":"570fd6c2d2720bc6458b457f","parentId":"61fcf31555324313dd16dc4d","slotId":"mod_scope","location":null},{"_id":"61fcf31555324313dd16dc4f","_tpl":"599860e986f7743bb57573a6","parentId":"61fcf31555324313dd16dc46","slotId":"mod_sight_rear","location":null},{"_id":"61fcf31555324313dd16dc50","_tpl":"59ccd11386f77428f24a488f","parentId":"61fcf31555324313dd16dc46","slotId":"mod_gas_block","location":null},{"_id":"61fcf31555324313dd16dc51","_tpl":"5648b4534bdc2d3d1c8b4580","parentId":"61fcf31555324313dd16dc50","slotId":"mod_handguard","location":null},{"_id":"61fcf31555324313dd16dc52","_tpl":"591af28e86f77414a27a9e1d","parentId":"61fcf31555324313dd16dc51","slotId":"mod_foregrip","location":null},{"_id":"61fcf31555324313dd16dc53","_tpl":"560d657b4bdc2da74d8b4572","parentId":"61fcf31555324313dd16dc51","slotId":"mod_tactical_001","location":null},{"_id":"61fcf31555324313dd16dc6a","_tpl":"5894a5b586f77426d2590767","parentId":"hideout","slotId":"hideout","upd":{"StackObjectsCount":1898}},{"_id":"61fcf31555324313dd16dc6c","_tpl":"5c0684e50db834002a12585a","parentId":"hideout","slotId":"hideout","upd":{"StackObjectsCount":1937}},{"_id":"61fcf31555324313dd16dc92","_tpl":"54491c4f4bdc2db1078b4568","parentId":"hideout","slotId":"hideout","location":null,"upd":{"BuyRestrictionMax":2,"BuyRestrictionCurrent":0,"StackObjectsCount":1463}},{"_id":"61fcf31555324313dd16dc93","_tpl":"55d4491a4bdc2d882f8b456e","parentId":"61fcf31555324313dd16dc92","slotId":"mod_barrel","location":null},{"_id":"61fcf31555324313dd16dc94","_tpl":"560838c94bdc2d77798b4569","parentId":"61fcf31555324313dd16dc93","slotId":"mod_muzzle","location":null},{"_id":"61fcf31555324313dd16dc95","_tpl":"55d45f484bdc2d972f8b456d","parentId":"61fcf31555324313dd16dc92","slotId":"mod_handguard","location":null},{"_id":"61fcf31555324313dd16dc96","_tpl":"588226d124597767ad33f787","parentId":"61fcf31555324313dd16dc95","slotId":"mod_foregrip","location":null},{"_id":"61fcf31555324313dd16dc97","_tpl":"57d17e212459775a1179a0f5","parentId":"61fcf31555324313dd16dc95","slotId":"mod_tactical_000","location":null},{"_id":"61fcf31555324313dd16dc98","_tpl":"59d790f486f77403cb06aec6","parentId":"61fcf31555324313dd16dc97","slotId":"mod_flashlight","location":null},{"_id":"61fcf31555324313dd16dc99","_tpl":"55d484b44bdc2d1d4e8b456d","parentId":"61fcf31555324313dd16dc92","slotId":"mod_magazine","location":null},{"_id":"61fcf31555324313dd16dc9a","_tpl":"56083be64bdc2d20478b456f","parentId":"61fcf31555324313dd16dc92","slotId":"mod_stock","location":null},{"_id":"61fcf31555324313dd16dc9b","_tpl":"55d48a634bdc2d8b2f8b456a","parentId":"61fcf31555324313dd16dc92","slotId":"mod_mount_001","location":null},{"_id":"61fcf31555324313dd16dc9c","_tpl":"5a33b2c9c4a282000c5a9511","parentId":"61fcf31555324313dd16dc9b","slotId":"mod_scope","location":null},{"_id":"61fcf31555324313dd16dc9d","_tpl":"5a32aa8bc4a2826c6e06d737","parentId":"61fcf31555324313dd16dc9c","slotId":"mod_scope","location":null},{"_id":"61fcf31555324313dd16dca1","_tpl":"5a7ad4af51dfba0013379717","parentId":"hideout","slotId":"hideout","upd":{"StackObjectsCount":5860}},{"_id":"61fcf31555324313dd16dcb6","_tpl":"571a12c42459771f627b58a0","parentId":"hideout","slotId":"hideout","location":null,"upd":{"FireMode":{"FireMode":"single"},"BuyRestrictionMax":2,"BuyRestrictionCurrent":0,"StackObjectsCount":1955}},{"_id":"61fcf31555324313dd16dcb7","_tpl":"571a26d524597720680fbe8a","parentId":"61fcf31555324313dd16dcb6","slotId":"mod_barrel","location":null},{"_id":"61fcf31555324313dd16dcb8","_tpl":"5c079ec50db834001966a706","parentId":"61fcf31555324313dd16dcb6","slotId":"mod_pistol_grip","location":null},{"_id":"61fcf31555324313dd16dcb9","_tpl":"571a29dc2459771fb2755a6a","parentId":"61fcf31555324313dd16dcb6","slotId":"mod_magazine","location":null},{"_id":"61fcf31555324313dd16dcba","_tpl":"5bffd7ed0db834001d23ebf9","parentId":"61fcf31555324313dd16dcb6","slotId":"mod_muzzle","location":null},{"_id":"61fcf31555324313dd16dcbb","_tpl":"5c079ed60db834001a66b372","parentId":"61fcf31555324313dd16dcb6","slotId":"mod_tactical","location":null},{"_id":"61fcf31555324313dd16dcd5","_tpl":"5a6f5e048dc32e00094b97da","parentId":"hideout","slotId":"hideout","upd":{"StackObjectsCount":5977}},{"_id":"61fcf31555324313dd16dced","_tpl":"56d59d3ad2720bdb418b4577","parentId":"hideout","slotId":"hideout","upd":{"UnlimitedCount":true,"StackObjectsCount":580000}},{"_id":"61fcf31555324313dd16dcef","_tpl":"59d64ec286f774171d1e0a42","parentId":"hideout","slotId":"hideout","upd":{"BuyRestrictionMax":4,"BuyRestrictionCurrent":0,"StackObjectsCount":1686}},{"_id":"61fcf31555324313dd16dcf3","_tpl":"59c6633186f7740cf0493bb9","parentId":"hideout","slotId":"hideout","upd":{"BuyRestrictionMax":4,"BuyRestrictionCurrent":0,"StackObjectsCount":6590}},{"_id":"61fcf31555324313dd16dcf7","_tpl":"5a718b548dc32e000d46d262","parentId":"hideout","slotId":"hideout","upd":{"StackObjectsCount":16311}},{"_id":"61fcf31555324313dd16dd03","_tpl":"5a7ae0c351dfba0017554310","parentId":"hideout","slotId":"hideout","location":null,"upd":{"BuyRestrictionMax":2,"BuyRestrictionCurrent":0,"StackObjectsCount":156}},{"_id":"61fcf31555324313dd16dd04","_tpl":"5a6b5f868dc32e000a311389","parentId":"61fcf31555324313dd16dd03","slotId":"mod_barrel","location":null},{"_id":"61fcf31555324313dd16dd05","_tpl":"5a7b4960e899ef197b331a2d","parentId":"61fcf31555324313dd16dd03","slotId":"mod_pistol_grip","location":null},{"_id":"61fcf31555324313dd16dd06","_tpl":"5a6f5e048dc32e00094b97da","parentId":"61fcf31555324313dd16dd03","slotId":"mod_reciever","location":null},{"_id":"61fcf31555324313dd16dd07","_tpl":"5a71e0fb8dc32e00094b97f2","parentId":"61fcf31555324313dd16dd06","slotId":"mod_sight_rear","location":null},{"_id":"61fcf31555324313dd16dd08","_tpl":"5a71e0048dc32e000c52ecc8","parentId":"61fcf31555324313dd16dd06","slotId":"mod_sight_front","location":null},{"_id":"61fcf31555324313dd16dd09","_tpl":"5a7b32a2e899ef00135e345a","parentId":"61fcf31555324313dd16dd06","slotId":"mod_muzzle","location":null},{"_id":"61fcf31555324313dd16dd0a","_tpl":"5a718f958dc32e00094b97e7","parentId":"61fcf31555324313dd16dd03","slotId":"mod_magazine","location":null},{"_id":"61fcf31555324313dd16dd0b","_tpl":"5a7b483fe899ef0016170d15","parentId":"61fcf31555324313dd16dd03","slotId":"mod_tactical","location":null},{"_id":"61fcf31555324313dd16dd1b","_tpl":"5a7ae0c351dfba0017554310","parentId":"hideout","slotId":"hideout","upd":{"StackObjectsCount":1956}},{"_id":"61fcf31555324313dd16dd27","_tpl":"544fb5454bdc2df8738b456a","parentId":"hideout","slotId":"hideout","upd":{"UnlimitedCount":true,"BuyRestrictionMax":3,"BuyRestrictionCurrent":0,"StackObjectsCount":580000}},{"_id":"61fcf31555324313dd16dd29","_tpl":"5b7bed205acfc400161d08cc","parentId":"hideout","slotId":"hideout","upd":{"StackObjectsCount":1995}},{"_id":"61fcf31555324313dd16dd47","_tpl":"55d4af3a4bdc2d972f8b456f","parentId":"hideout","slotId":"hideout","upd":{"StackObjectsCount":14975}},{"_id":"61fcf31555324313dd16dd75","_tpl":"590c2e1186f77425357b6124","parentId":"hideout","slotId":"hideout","upd":{"BuyRestrictionMax":2,"BuyRestrictionCurrent":0,"StackObjectsCount":8319}},{"_id":"61fcf31555324313dd16dd7b","_tpl":"57235b6f24597759bf5a30f1","parentId":"hideout","slotId":"hideout","upd":{"BuyRestrictionMax":1,"BuyRestrictionCurrent":0,"StackObjectsCount":309}},{"_id":"61fcf31555324313dd16dd8b","_tpl":"59d64fc686f774171b243fe2","parentId":"hideout","slotId":"hideout","upd":{"StackObjectsCount":1951}},{"_id":"61fcf31555324313dd16dd99","_tpl":"5ba26383d4351e00334c93d9","parentId":"hideout","slotId":"hideout","location":null,"upd":{"BuyRestrictionMax":1,"BuyRestrictionCurrent":0,"StackObjectsCount":1984}},{"_id":"61fcf31555324313dd16dd9a","_tpl":"5ba26586d4351e44f824b340","parentId":"61fcf31555324313dd16dd99","slotId":"mod_magazine","location":null},{"_id":"61fcf31555324313dd16dd9b","_tpl":"5ba26acdd4351e003562908e","parentId":"61fcf31555324313dd16dd99","slotId":"mod_muzzle","location":null},{"_id":"61fcf31555324313dd16dd9c","_tpl":"5ba26ae8d4351e00367f9bdb","parentId":"61fcf31555324313dd16dd9b","slotId":"mod_muzzle","location":null},{"_id":"61fcf31555324313dd16dd9d","_tpl":"58d39d3d86f77445bb794ae7","parentId":"61fcf31555324313dd16dd99","slotId":"mod_scope","location":null},{"_id":"61fcf31555324313dd16dd9e","_tpl":"58d39b0386f77443380bf13c","parentId":"61fcf31555324313dd16dd9d","slotId":"mod_scope","location":null},{"_id":"61fcf31555324313dd16dd9f","_tpl":"58d399e486f77442e0016fe7","parentId":"61fcf31555324313dd16dd9e","slotId":"mod_scope","location":null},{"_id":"61fcf31555324313dd16dda0","_tpl":"544909bb4bdc2d6f028b4577","parentId":"61fcf31555324313dd16dd99","slotId":"mod_tactical_000","location":null},{"_id":"61fcf31555324313dd16dda1","_tpl":"57d17e212459775a1179a0f5","parentId":"61fcf31555324313dd16dd99","slotId":"mod_tactical_002","location":null},{"_id":"61fcf31555324313dd16dda2","_tpl":"57d17c5e2459775a5c57d17d","parentId":"61fcf31555324313dd16dda1","slotId":"mod_flashlight","location":null},{"_id":"61fcf31555324313dd16dda3","_tpl":"5bcf0213d4351e0085327c17","parentId":"61fcf31555324313dd16dd99","slotId":"mod_stock","location":null},{"_id":"61fcf31555324313dd16dda5","_tpl":"5c079ed60db834001a66b372","parentId":"hideout","slotId":"hideout","upd":{"BuyRestrictionMax":4,"BuyRestrictionCurrent":0,"StackObjectsCount":1924}},{"_id":"61fcf31555324313dd16dda7","_tpl":"58948c8e86f77409493f7266","parentId":"hideout","slotId":"hideout","location":null,"upd":{"BuyRestrictionMax":2,"BuyRestrictionCurrent":0,"StackObjectsCount":148}},{"_id":"61fcf31555324313dd16dda8","_tpl":"57c55efc2459772d2c6271e7","parentId":"61fcf31555324313dd16dda7","slotId":"mod_pistol_grip","location":null},{"_id":"61fcf31555324313dd16dda9","_tpl":"5894a05586f774094708ef75","parentId":"61fcf31555324313dd16dda7","slotId":"mod_magazine","location":null},{"_id":"61fcf31555324313dd16ddaa","_tpl":"5894a5b586f77426d2590767","parentId":"61fcf31555324313dd16dda7","slotId":"mod_reciever","location":null},{"_id":"61fcf31555324313dd16ddab","_tpl":"57adff4f24597737f373b6e6","parentId":"61fcf31555324313dd16ddaa","slotId":"mod_scope","location":null},{"_id":"61fcf31555324313dd16ddac","_tpl":"58d2664f86f7747fec5834f6","parentId":"61fcf31555324313dd16ddab","slotId":"mod_scope","location":null},{"_id":"61fcf31555324313dd16ddad","_tpl":"58d268fc86f774111273f8c2","parentId":"61fcf31555324313dd16ddac","slotId":"mod_scope","location":null},{"_id":"61fcf31555324313dd16ddae","_tpl":"58aeaaa886f7744fc1560f81","parentId":"61fcf31555324313dd16ddaa","slotId":"mod_barrel","location":null},{"_id":"61fcf31555324313dd16ddaf","_tpl":"58aeac1b86f77457c419f475","parentId":"61fcf31555324313dd16ddae","slotId":"mod_muzzle","location":null},{"_id":"61fcf31555324313dd16ddb0","_tpl":"5894a42086f77426d2590762","parentId":"61fcf31555324313dd16ddaa","slotId":"mod_handguard","location":null},{"_id":"61fcf31555324313dd16ddb1","_tpl":"58a56f8d86f774651579314c","parentId":"61fcf31555324313dd16ddb0","slotId":"mod_mount_000","location":null},{"_id":"61fcf31555324313dd16ddb2","_tpl":"5a7b483fe899ef0016170d15","parentId":"61fcf31555324313dd16ddb1","slotId":"mod_tactical","location":null},{"_id":"61fcf31555324313dd16ddb3","_tpl":"58a5c12e86f7745d585a2b9e","parentId":"61fcf31555324313dd16ddb0","slotId":"mod_mount_001","location":null},{"_id":"61fcf31555324313dd16ddb4","_tpl":"59f8a37386f7747af3328f06","parentId":"61fcf31555324313dd16ddb3","slotId":"mod_foregrip","location":null},{"_id":"61fcf31555324313dd16ddb5","_tpl":"58ac1bf086f77420ed183f9f","parentId":"61fcf31555324313dd16dda7","slotId":"mod_stock","location":null},{"_id":"61fcf31555324313dd16ddb6","_tpl":"591aef7986f774139d495f03","parentId":"61fcf31555324313dd16ddb5","slotId":"mod_stock","location":null},{"_id":"61fcf31555324313dd16ddb7","_tpl":"58949edd86f77409483e16a9","parentId":"61fcf31555324313dd16dda7","slotId":"mod_charge","location":null},{"_id":"61fcf31555324313dd16ddcc","_tpl":"5b7d678a5acfc4001a5c4022","parentId":"hideout","slotId":"hideout","upd":{"StackObjectsCount":1987}},{"_id":"61fcf31555324313dd16ddce","_tpl":"5aafbde786f774389d0cbc0f","parentId":"hideout","slotId":"hideout","upd":{"BuyRestrictionMax":1,"BuyRestrictionCurrent":0,"StackObjectsCount":5214}},{"_id":"61fcf31655324313dd16de4c","_tpl":"55d44fd14bdc2d962f8b456e","parentId":"hideout","slotId":"hideout","upd":{"BuyRestrictionMax":4,"BuyRestrictionCurrent":0,"StackObjectsCount":1796}},{"_id":"61fcf31655324313dd16de54","_tpl":"55d45f484bdc2d972f8b456d","parentId":"hideout","slotId":"hideout","upd":{"StackObjectsCount":19751}},{"_id":"61fcf31655324313dd16de76","_tpl":"5a7b483fe899ef0016170d15","parentId":"hideout","slotId":"hideout","upd":{"StackObjectsCount":5076}},{"_id":"61fcf31655324313dd16de88","_tpl":"56d5a1f7d2720bb3418b456a","parentId":"hideout","slotId":"hideout","upd":{"BuyRestrictionMax":5,"BuyRestrictionCurrent":0,"StackObjectsCount":1998}},{"_id":"61fcf31655324313dd16dea2","_tpl":"544a38634bdc2d58388b4568","parentId":"hideout","slotId":"hideout","upd":{"BuyRestrictionMax":4,"BuyRestrictionCurrent":0,"StackObjectsCount":19974}},{"_id":"61fcf31755324313dd16dfec","_tpl":"57ffa9f4245977728561e844","parentId":"hideout","slotId":"hideout","upd":{"BuyRestrictionMax":2,"BuyRestrictionCurrent":0,"StackObjectsCount":5998}},{"_id":"61fcf31755324313dd16e028","_tpl":"5af04b6486f774195a3ebb49","parentId":"hideout","slotId":"hideout","upd":{"BuyRestrictionMax":2,"BuyRestrictionCurrent":0,"StackObjectsCount":2903}},{"_id":"61fcf31755324313dd16e02a","_tpl":"5fc3e272f8b6a877a729eac5","parentId":"hideout","slotId":"hideout","location":null,"upd":{"Foldable":{"Folded":false},"FireMode":{"FireMode":"single"},"BuyRestrictionMax":1,"BuyRestrictionCurrent":0,"StackObjectsCount":19819}},{"_id":"61fcf31755324313dd16e02b","_tpl":"5fc3e466187fea44d52eda90","parentId":"61fcf31755324313dd16e02a","slotId":"mod_magazine","location":null},{"_id":"61fcf31755324313dd16e02c","_tpl":"5fc3e4ee7283c4046c5814af","parentId":"61fcf31755324313dd16e02a","slotId":"mod_stock","location":null},{"_id":"61fcf31755324313dd16e02d","_tpl":"5fc3e4a27283c4046c5814ab","parentId":"61fcf31755324313dd16e02a","slotId":"mod_barrel","location":null},{"_id":"61fcf31755324313dd16e02e","_tpl":"5fc53954f8b6a877a729eaeb","parentId":"61fcf31755324313dd16e02a","slotId":"mod_mount_000","location":null},{"_id":"61fcf31755324313dd16e02f","_tpl":"5fc5396e900b1d5091531e72","parentId":"61fcf31755324313dd16e02a","slotId":"mod_mount_001","location":null},{"_id":"61fcf31755324313dd16e030","_tpl":"5fc5396e900b1d5091531e72","parentId":"61fcf31755324313dd16e02a","slotId":"mod_mount_002","location":null},{"_id":"61fcf31755324313dd16e036","_tpl":"5b7be47f5acfc400170e2dd2","parentId":"hideout","slotId":"hideout","upd":{"BuyRestrictionMax":4,"BuyRestrictionCurrent":0,"StackObjectsCount":4903}},{"_id":"61fcf31755324313dd16e038","_tpl":"5b7be4895acfc400170e2dd5","parentId":"hideout","slotId":"hideout","upd":{"BuyRestrictionMax":4,"BuyRestrictionCurrent":0,"StackObjectsCount":5769}},{"_id":"61fcf31755324313dd16e04e","_tpl":"59e6687d86f77411d949b251","parentId":"hideout","slotId":"hideout","location":null,"upd":{"BuyRestrictionMax":2,"BuyRestrictionCurrent":0,"StackObjectsCount":1995}},{"_id":"61fcf31755324313dd16e04f","_tpl":"59e649f986f77411d949b246","parentId":"61fcf31755324313dd16e04e","slotId":"mod_gas_block","location":null},{"_id":"61fcf31755324313dd16e050","_tpl":"59e898ee86f77427614bd225","parentId":"61fcf31755324313dd16e04f","slotId":"mod_handguard","location":null},{"_id":"61fcf31755324313dd16e051","_tpl":"59e8a00d86f7742ad93b569c","parentId":"61fcf31755324313dd16e04e","slotId":"mod_muzzle","location":null},{"_id":"61fcf31755324313dd16e052","_tpl":"59e6318286f77444dd62c4cc","parentId":"61fcf31755324313dd16e04e","slotId":"mod_pistol_grip","location":null},{"_id":"61fcf31755324313dd16e053","_tpl":"59e6449086f7746c9f75e822","parentId":"61fcf31755324313dd16e04e","slotId":"mod_reciever","location":null},{"_id":"61fcf31755324313dd16e054","_tpl":"59e8977386f77415a553c453","parentId":"61fcf31755324313dd16e04e","slotId":"mod_sight_rear","location":null},{"_id":"61fcf31755324313dd16e055","_tpl":"59e89d0986f77427600d226e","parentId":"61fcf31755324313dd16e04e","slotId":"mod_stock","location":null},{"_id":"61fcf31755324313dd16e056","_tpl":"59d625f086f774661516605d","parentId":"61fcf31755324313dd16e04e","slotId":"mod_magazine","location":null},{"_id":"61fcf31755324313dd16e058","_tpl":"5644bd2b4bdc2d3b4c8b4572","parentId":"hideout","slotId":"hideout","location":null,"upd":{"FireMode":{"FireMode":"single"},"BuyRestrictionMax":2,"BuyRestrictionCurrent":0,"StackObjectsCount":2950}},{"_id":"61fcf31755324313dd16e059","_tpl":"59c6633186f7740cf0493bb9","parentId":"61fcf31755324313dd16e058","slotId":"mod_gas_block","location":null},{"_id":"61fcf31755324313dd16e05a","_tpl":"5648b0744bdc2d363b8b4578","parentId":"61fcf31755324313dd16e059","slotId":"mod_handguard","location":null},{"_id":"61fcf31755324313dd16e05b","_tpl":"5649aa744bdc2ded0b8b457e","parentId":"61fcf31755324313dd16e058","slotId":"mod_muzzle","location":null},{"_id":"61fcf31755324313dd16e05c","_tpl":"5649ad3f4bdc2df8348b4585","parentId":"61fcf31755324313dd16e058","slotId":"mod_pistol_grip","location":null},{"_id":"61fcf31755324313dd16e05d","_tpl":"5649af094bdc2df8348b4586","parentId":"61fcf31755324313dd16e058","slotId":"mod_reciever","location":null},{"_id":"61fcf31755324313dd16e05e","_tpl":"5649b0544bdc2d1b2b8b458a","parentId":"61fcf31755324313dd16e058","slotId":"mod_sight_rear","location":null},{"_id":"61fcf31755324313dd16e05f","_tpl":"5649b1c04bdc2d16268b457c","parentId":"61fcf31755324313dd16e058","slotId":"mod_stock","location":null},{"_id":"61fcf31755324313dd16e060","_tpl":"564ca99c4bdc2d16268b4589","parentId":"61fcf31755324313dd16e058","slotId":"mod_magazine","location":null}],"barter_scheme":{"61fcf31455324313dd16dafa":[[{"count":1,"_tpl":"59e35de086f7741778269d84"},{"count":1,"_tpl":"56742c324bdc2d150f8b456d"}]],"61fcf31455324313dd16dafc":[[{"count":16.87,"_tpl":"569668774bdc2da2298b4568"}]],"61fcf31455324313dd16db06":[[{"count":2242,"_tpl":"5449016a4bdc2d6f028b456f"}]],"61fcf31455324313dd16db4b":[[{"count":15526,"_tpl":"5449016a4bdc2d6f028b456f"}]],"61fcf31455324313dd16db52":[[{"count":5327,"_tpl":"5449016a4bdc2d6f028b456f"}]],"61fcf31455324313dd16db80":[[{"count":5,"_tpl":"5d235b4d86f7742e017bc88a"}]],"61fcf31455324313dd16dbab":[[{"count":13.96,"_tpl":"569668774bdc2da2298b4568"}]],"61fcf31455324313dd16dbc9":[[{"count":110,"_tpl":"5449016a4bdc2d6f028b456f"}]],"61fcf31455324313dd16dc1a":[[{"count":2802,"_tpl":"5449016a4bdc2d6f028b456f"}]],"61fcf31455324313dd16dc1c":[[{"count":16893,"_tpl":"5449016a4bdc2d6f028b456f"}]],"61fcf31455324313dd16dc34":[[{"count":4510,"_tpl":"5449016a4bdc2d6f028b456f"}]],"61fcf31555324313dd16dc42":[[{"count":3135,"_tpl":"5449016a4bdc2d6f028b456f"}]],"61fcf31555324313dd16dc46":[[{"count":1,"_tpl":"59faf7ca86f7740dbe19f6c2"},{"count":1,"_tpl":"5d235b4d86f7742e017bc88a"}]],"61fcf31555324313dd16dc6a":[[{"count":31.35,"_tpl":"569668774bdc2da2298b4568"}]],"61fcf31555324313dd16dc6c":[[{"count":3024,"_tpl":"5449016a4bdc2d6f028b456f"}]],"61fcf31555324313dd16dc92":[[{"count":2,"_tpl":"5af04b6486f774195a3ebb49"},{"count":1,"_tpl":"590c2d8786f774245b1f03f3"}]],"61fcf31555324313dd16dca1":[[{"count":36.12,"_tpl":"569668774bdc2da2298b4568"}]],"61fcf31555324313dd16dcb6":[[{"count":1,"_tpl":"5c06779c86f77426e00dd782"},{"count":2,"_tpl":"5c06782b86f77426df5407d2"}]],"61fcf31555324313dd16dcd5":[[{"count":27.77,"_tpl":"569668774bdc2da2298b4568"}]],"61fcf31555324313dd16dced":[[{"count":70,"_tpl":"5449016a4bdc2d6f028b456f"}]],"61fcf31555324313dd16dcef":[[{"count":2302,"_tpl":"5449016a4bdc2d6f028b456f"}]],"61fcf31555324313dd16dcf3":[[{"count":2322,"_tpl":"5449016a4bdc2d6f028b456f"}]],"61fcf31555324313dd16dcf7":[[{"count":1654,"_tpl":"5449016a4bdc2d6f028b456f"}]],"61fcf31555324313dd16dd03":[[{"count":3,"_tpl":"5aa2b9ede5b5b000137b758b"}]],"61fcf31555324313dd16dd1b":[[{"count":7401,"_tpl":"5449016a4bdc2d6f028b456f"}]],"61fcf31555324313dd16dd27":[[{"count":17903,"_tpl":"5449016a4bdc2d6f028b456f"}]],"61fcf31555324313dd16dd29":[[{"count":2688,"_tpl":"5449016a4bdc2d6f028b456f"}]],"61fcf31555324313dd16dd47":[[{"count":672,"_tpl":"5449016a4bdc2d6f028b456f"}]],"61fcf31555324313dd16dd75":[[{"count":1,"_tpl":"590c2b4386f77425357b6123"},{"count":1,"_tpl":"590c2d8786f774245b1f03f3"},{"count":1,"_tpl":"590c311186f77424d1667482"},{"count":1,"_tpl":"5734795124597738002c6176"},{"count":1,"_tpl":"590c2c9c86f774245b1f03f2"}]],"61fcf31555324313dd16dd7b":[[{"count":2,"_tpl":"56742c324bdc2d150f8b456d"},{"count":3,"_tpl":"5d1b309586f77425227d1676"}]],"61fcf31555324313dd16dd8b":[[{"count":681,"_tpl":"5449016a4bdc2d6f028b456f"}]],"61fcf31555324313dd16dd99":[[{"count":5,"_tpl":"5d1b304286f774253763a528"},{"count":1,"_tpl":"5d1b2ffd86f77425243e8d17"}]],"61fcf31555324313dd16dda5":[[{"count":5152,"_tpl":"5449016a4bdc2d6f028b456f"}]],"61fcf31555324313dd16dda7":[[{"count":5,"_tpl":"5734781f24597737e04bf32a"},{"count":5,"_tpl":"590a3d9c86f774385926e510"},{"count":2,"_tpl":"5d1c819a86f774771b0acd6c"}]],"61fcf31555324313dd16ddcc":[[{"count":1232,"_tpl":"5449016a4bdc2d6f028b456f"}]],"61fcf31555324313dd16ddce":[[{"count":2,"_tpl":"60391a8b3364dc22b04d0ce5"},{"count":2,"_tpl":"5d6fc78386f77449d825f9dc"}]],"61fcf31655324313dd16de4c":[[{"count":821,"_tpl":"5449016a4bdc2d6f028b456f"}]],"61fcf31655324313dd16de54":[[{"count":1,"_tpl":"590a386e86f77429692b27ab"}]],"61fcf31655324313dd16de76":[[{"count":18866,"_tpl":"5449016a4bdc2d6f028b456f"}]],"61fcf31655324313dd16de88":[[{"count":1751,"_tpl":"5449016a4bdc2d6f028b456f"}]],"61fcf31655324313dd16dea2":[[{"count":1501,"_tpl":"5449016a4bdc2d6f028b456f"}]],"61fcf31755324313dd16dfec":[[{"count":1,"_tpl":"5e2aedd986f7746d404f3aa4"},{"count":2,"_tpl":"5672cb304bdc2dc2088b456a"}]],"61fcf31755324313dd16e028":[[{"count":1,"_tpl":"590c2b4386f77425357b6123"},{"count":1,"_tpl":"5d40425986f7743185265461"},{"count":1,"_tpl":"5d1b31ce86f7742523398394"}]],"61fcf31755324313dd16e02a":[[{"count":1,"_tpl":"5734781f24597737e04bf32a"},{"count":1,"_tpl":"590a386e86f77429692b27ab"},{"count":2,"_tpl":"5c06782b86f77426df5407d2"}]],"61fcf31755324313dd16e036":[[{"count":1,"_tpl":"590c2c9c86f774245b1f03f2"}]],"61fcf31755324313dd16e038":[[{"count":1,"_tpl":"5909e99886f7740c983b9984"}]],"61fcf31755324313dd16e04e":[[{"count":2,"_tpl":"59e6687d86f77411d949b251"}]],"61fcf31755324313dd16e058":[[{"count":1,"_tpl":"5ab8e9fcd8ce870019439434"}]]},"loyal_level_items":{"61fcf31455324313dd16dae6":3,"61fcf31455324313dd16dae8":2,"61fcf31455324313dd16daea":3,"61fcf31455324313dd16daec":3,"61fcf31455324313dd16daee":3,"61fcf31455324313dd16daf0":2,"61fcf31455324313dd16dafa":1,"61fcf31455324313dd16dafc":1,"61fcf31455324313dd16dafe":3,"61fcf31455324313dd16db00":4,"61fcf31455324313dd16db02":3,"61fcf31455324313dd16db04":4,"61fcf31455324313dd16db06":1,"61fcf31455324313dd16db08":3,"61fcf31455324313dd16db0a":4,"61fcf31455324313dd16db0c":4,"61fcf31455324313dd16db15":4,"61fcf31455324313dd16db17":2,"61fcf31455324313dd16db19":2,"61fcf31455324313dd16db25":2,"61fcf31455324313dd16db27":2,"61fcf31455324313dd16db29":4,"61fcf31455324313dd16db2b":2,"61fcf31455324313dd16db3f":4,"61fcf31455324313dd16db41":2,"61fcf31455324313dd16db43":3,"61fcf31455324313dd16db45":3,"61fcf31455324313dd16db47":2,"61fcf31455324313dd16db49":2,"61fcf31455324313dd16db4b":1,"61fcf31455324313dd16db52":1,"61fcf31455324313dd16db54":4,"61fcf31455324313dd16db62":4,"61fcf31455324313dd16db64":3,"61fcf31455324313dd16db72":2,"61fcf31455324313dd16db74":4,"61fcf31455324313dd16db76":2,"61fcf31455324313dd16db78":2,"61fcf31455324313dd16db7a":4,"61fcf31455324313dd16db7c":3,"61fcf31455324313dd16db7e":3,"61fcf31455324313dd16db80":1,"61fcf31455324313dd16db85":2,"61fcf31455324313dd16db87":3,"61fcf31455324313dd16db89":2,"61fcf31455324313dd16db8b":2,"61fcf31455324313dd16db8d":2,"61fcf31455324313dd16db8f":3,"61fcf31455324313dd16db91":2,"61fcf31455324313dd16db93":3,"61fcf31455324313dd16db95":1,"61fcf31455324313dd16db97":2,"61fcf31455324313dd16dba0":3,"61fcf31455324313dd16dba2":2,"61fcf31455324313dd16dbab":1,"61fcf31455324313dd16dbad":3,"61fcf31455324313dd16dbaf":4,"61fcf31455324313dd16dbb1":3,"61fcf31455324313dd16dbbb":2,"61fcf31455324313dd16dbc3":2,"61fcf31455324313dd16dbc5":4,"61fcf31455324313dd16dbc7":3,"61fcf31455324313dd16dbc9":1,"61fcf31455324313dd16dbcb":3,"61fcf31455324313dd16dbda":2,"61fcf31455324313dd16dbdc":3,"61fcf31455324313dd16dbde":3,"61fcf31455324313dd16dbeb":3,"61fcf31455324313dd16dbed":4,"61fcf31455324313dd16dbef":1,"61fcf31455324313dd16dbf1":3,"61fcf31455324313dd16dbf3":3,"61fcf31455324313dd16dbf5":4,"61fcf31455324313dd16dbf7":4,"61fcf31455324313dd16dbf9":3,"61fcf31455324313dd16dbfb":2,"61fcf31455324313dd16dbfd":4,"61fcf31455324313dd16dbff":2,"61fcf31455324313dd16dc08":4,"61fcf31455324313dd16dc0a":2,"61fcf31455324313dd16dc0c":3,"61fcf31455324313dd16dc0e":2,"61fcf31455324313dd16dc10":2,"61fcf31455324313dd16dc18":3,"61fcf31455324313dd16dc1a":1,"61fcf31455324313dd16dc1c":1,"61fcf31455324313dd16dc1e":4,"61fcf31455324313dd16dc20":4,"61fcf31455324313dd16dc22":3,"61fcf31455324313dd16dc24":4,"61fcf31455324313dd16dc26":2,"61fcf31455324313dd16dc28":2,"61fcf31455324313dd16dc2a":4,"61fcf31455324313dd16dc2c":2,"61fcf31455324313dd16dc2e":2,"61fcf31455324313dd16dc30":3,"61fcf31455324313dd16dc32":3,"61fcf31455324313dd16dc34":1,"61fcf31455324313dd16dc36":3,"61fcf31455324313dd16dc38":3,"61fcf31455324313dd16dc3a":2,"61fcf31455324313dd16dc3c":3,"61fcf31455324313dd16dc3e":2,"61fcf31555324313dd16dc40":3,"61fcf31555324313dd16dc42":1,"61fcf31555324313dd16dc44":3,"61fcf31555324313dd16dc46":1,"61fcf31555324313dd16dc55":3,"61fcf31555324313dd16dc57":3,"61fcf31555324313dd16dc59":3,"61fcf31555324313dd16dc5b":3,"61fcf31555324313dd16dc66":2,"61fcf31555324313dd16dc68":3,"61fcf31555324313dd16dc6a":1,"61fcf31555324313dd16dc6c":1,"61fcf31555324313dd16dc6e":4,"61fcf31555324313dd16dc70":4,"61fcf31555324313dd16dc72":3,"61fcf31555324313dd16dc7f":3,"61fcf31555324313dd16dc81":3,"61fcf31555324313dd16dc92":1,"61fcf31555324313dd16dc9f":3,"61fcf31555324313dd16dca1":1,"61fcf31555324313dd16dca3":2,"61fcf31555324313dd16dca5":3,"61fcf31555324313dd16dca7":4,"61fcf31555324313dd16dca9":2,"61fcf31555324313dd16dcab":3,"61fcf31555324313dd16dcad":3,"61fcf31555324313dd16dcb6":1,"61fcf31555324313dd16dcbd":2,"61fcf31555324313dd16dcc7":2,"61fcf31555324313dd16dcc9":4,"61fcf31555324313dd16dccb":3,"61fcf31555324313dd16dccd":2,"61fcf31555324313dd16dccf":2,"61fcf31555324313dd16dcd1":4,"61fcf31555324313dd16dcd3":3,"61fcf31555324313dd16dcd5":1,"61fcf31555324313dd16dcd7":1,"61fcf31555324313dd16dce3":3,"61fcf31555324313dd16dced":1,"61fcf31555324313dd16dcef":1,"61fcf31555324313dd16dcf1":4,"61fcf31555324313dd16dcf3":1,"61fcf31555324313dd16dcf5":3,"61fcf31555324313dd16dcf7":1,"61fcf31555324313dd16dcf9":4,"61fcf31555324313dd16dcfb":2,"61fcf31555324313dd16dcfd":3,"61fcf31555324313dd16dcff":2,"61fcf31555324313dd16dd01":4,"61fcf31555324313dd16dd03":1,"61fcf31555324313dd16dd0d":2,"61fcf31555324313dd16dd17":4,"61fcf31555324313dd16dd19":2,"61fcf31555324313dd16dd1b":1,"61fcf31555324313dd16dd1d":3,"61fcf31555324313dd16dd1f":4,"61fcf31555324313dd16dd21":3,"61fcf31555324313dd16dd23":3,"61fcf31555324313dd16dd25":2,"61fcf31555324313dd16dd27":1,"61fcf31555324313dd16dd29":1,"61fcf31555324313dd16dd2b":3,"61fcf31555324313dd16dd2d":3,"61fcf31555324313dd16dd2f":4,"61fcf31555324313dd16dd31":3,"61fcf31555324313dd16dd33":4,"61fcf31555324313dd16dd35":2,"61fcf31555324313dd16dd37":3,"61fcf31555324313dd16dd39":2,"61fcf31555324313dd16dd3b":3,"61fcf31555324313dd16dd3d":3,"61fcf31555324313dd16dd47":1,"61fcf31555324313dd16dd49":3,"61fcf31555324313dd16dd4b":3,"61fcf31555324313dd16dd56":4,"61fcf31555324313dd16dd61":3,"61fcf31555324313dd16dd63":2,"61fcf31555324313dd16dd65":4,"61fcf31555324313dd16dd67":3,"61fcf31555324313dd16dd69":3,"61fcf31555324313dd16dd6b":4,"61fcf31555324313dd16dd6d":4,"61fcf31555324313dd16dd6f":3,"61fcf31555324313dd16dd71":2,"61fcf31555324313dd16dd73":2,"61fcf31555324313dd16dd75":1,"61fcf31555324313dd16dd77":3,"61fcf31555324313dd16dd79":4,"61fcf31555324313dd16dd7b":1,"61fcf31555324313dd16dd7d":4,"61fcf31555324313dd16dd7f":4,"61fcf31555324313dd16dd81":2,"61fcf31555324313dd16dd83":2,"61fcf31555324313dd16dd85":4,"61fcf31555324313dd16dd87":4,"61fcf31555324313dd16dd89":2,"61fcf31555324313dd16dd8b":1,"61fcf31555324313dd16dd8d":4,"61fcf31555324313dd16dd8f":3,"61fcf31555324313dd16dd91":2,"61fcf31555324313dd16dd93":2,"61fcf31555324313dd16dd95":2,"61fcf31555324313dd16dd97":3,"61fcf31555324313dd16dd99":1,"61fcf31555324313dd16dda5":1,"61fcf31555324313dd16dda7":1,"61fcf31555324313dd16ddb9":2,"61fcf31555324313dd16ddbb":2,"61fcf31555324313dd16ddc4":3,"61fcf31555324313dd16ddc6":2,"61fcf31555324313dd16ddc8":3,"61fcf31555324313dd16ddca":2,"61fcf31555324313dd16ddcc":1,"61fcf31555324313dd16ddce":1,"61fcf31555324313dd16ddd0":3,"61fcf31555324313dd16ddd2":2,"61fcf31555324313dd16ddd4":2,"61fcf31555324313dd16ddd6":4,"61fcf31555324313dd16ddd8":2,"61fcf31555324313dd16ddec":2,"61fcf31555324313dd16ddee":3,"61fcf31555324313dd16ddf0":4,"61fcf31555324313dd16de00":3,"61fcf31555324313dd16de02":4,"61fcf31555324313dd16de04":3,"61fcf31555324313dd16de06":3,"61fcf31555324313dd16de0d":4,"61fcf31555324313dd16de0f":3,"61fcf31555324313dd16de11":3,"61fcf31555324313dd16de13":2,"61fcf31555324313dd16de15":3,"61fcf31655324313dd16de17":3,"61fcf31655324313dd16de19":3,"61fcf31655324313dd16de1b":2,"61fcf31655324313dd16de1d":2,"61fcf31655324313dd16de1f":2,"61fcf31655324313dd16de21":2,"61fcf31655324313dd16de23":2,"61fcf31655324313dd16de2e":3,"61fcf31655324313dd16de30":2,"61fcf31655324313dd16de32":4,"61fcf31655324313dd16de34":2,"61fcf31655324313dd16de36":4,"61fcf31655324313dd16de38":2,"61fcf31655324313dd16de3a":3,"61fcf31655324313dd16de3c":2,"61fcf31655324313dd16de3e":2,"61fcf31655324313dd16de40":3,"61fcf31655324313dd16de42":2,"61fcf31655324313dd16de44":2,"61fcf31655324313dd16de46":2,"61fcf31655324313dd16de48":2,"61fcf31655324313dd16de4a":2,"61fcf31655324313dd16de4c":1,"61fcf31655324313dd16de4e":3,"61fcf31655324313dd16de50":2,"61fcf31655324313dd16de52":4,"61fcf31655324313dd16de54":1,"61fcf31655324313dd16de56":2,"61fcf31655324313dd16de58":3,"61fcf31655324313dd16de5a":4,"61fcf31655324313dd16de5c":3,"61fcf31655324313dd16de5e":2,"61fcf31655324313dd16de60":4,"61fcf31655324313dd16de62":3,"61fcf31655324313dd16de64":2,"61fcf31655324313dd16de66":2,"61fcf31655324313dd16de6c":3,"61fcf31655324313dd16de6e":4,"61fcf31655324313dd16de70":2,"61fcf31655324313dd16de72":3,"61fcf31655324313dd16de74":2,"61fcf31655324313dd16de76":1,"61fcf31655324313dd16de78":3,"61fcf31655324313dd16de7a":3,"61fcf31655324313dd16de7c":2,"61fcf31655324313dd16de7e":4,"61fcf31655324313dd16de80":2,"61fcf31655324313dd16de82":2,"61fcf31655324313dd16de84":3,"61fcf31655324313dd16de86":3,"61fcf31655324313dd16de88":1,"61fcf31655324313dd16de8a":3,"61fcf31655324313dd16de8c":3,"61fcf31655324313dd16de8e":3,"61fcf31655324313dd16de90":2,"61fcf31655324313dd16de92":3,"61fcf31655324313dd16de94":4,"61fcf31655324313dd16de96":3,"61fcf31655324313dd16de98":2,"61fcf31655324313dd16de9a":3,"61fcf31655324313dd16de9c":4,"61fcf31655324313dd16de9e":2,"61fcf31655324313dd16dea0":3,"61fcf31655324313dd16dea2":1,"61fcf31655324313dd16dea4":4,"61fcf31655324313dd16dea6":4,"61fcf31655324313dd16dea8":4,"61fcf31655324313dd16deaa":4,"61fcf31655324313dd16deac":4,"61fcf31655324313dd16deae":3,"61fcf31655324313dd16deb0":3,"61fcf31655324313dd16deb2":3,"61fcf31655324313dd16deb4":4,"61fcf31655324313dd16deb6":2,"61fcf31655324313dd16deb8":2,"61fcf31655324313dd16deba":4,"61fcf31655324313dd16debc":2,"61fcf31655324313dd16debe":2,"61fcf31655324313dd16dec0":3,"61fcf31655324313dd16dec2":3,"61fcf31655324313dd16dec4":4,"61fcf31655324313dd16dec6":3,"61fcf31655324313dd16dec8":2,"61fcf31655324313dd16deca":4,"61fcf31655324313dd16decc":4,"61fcf31655324313dd16dece":2,"61fcf31655324313dd16ded0":3,"61fcf31655324313dd16ded2":2,"61fcf31655324313dd16ded4":3,"61fcf31655324313dd16ded6":3,"61fcf31655324313dd16ded8":2,"61fcf31655324313dd16deda":4,"61fcf31655324313dd16dedc":3,"61fcf31655324313dd16dede":3,"61fcf31655324313dd16dee0":4,"61fcf31655324313dd16dee2":3,"61fcf31655324313dd16dee4":4,"61fcf31655324313dd16dee6":4,"61fcf31655324313dd16dee8":4,"61fcf31655324313dd16deea":4,"61fcf31655324313dd16deec":3,"61fcf31655324313dd16deee":2,"61fcf31655324313dd16def5":4,"61fcf31655324313dd16def7":3,"61fcf31655324313dd16def9":3,"61fcf31655324313dd16defb":4,"61fcf31655324313dd16defd":4,"61fcf31655324313dd16deff":3,"61fcf31655324313dd16df01":3,"61fcf31655324313dd16df03":4,"61fcf31655324313dd16df05":3,"61fcf31655324313dd16df07":4,"61fcf31655324313dd16df09":4,"61fcf31655324313dd16df0b":3,"61fcf31655324313dd16df0d":4,"61fcf31655324313dd16df0f":3,"61fcf31655324313dd16df11":3,"61fcf31655324313dd16df13":4,"61fcf31655324313dd16df15":3,"61fcf31655324313dd16df17":3,"61fcf31655324313dd16df19":4,"61fcf31655324313dd16df1b":3,"61fcf31655324313dd16df1d":4,"61fcf31655324313dd16df1f":3,"61fcf31655324313dd16df21":3,"61fcf31655324313dd16df23":4,"61fcf31655324313dd16df25":3,"61fcf31655324313dd16df27":3,"61fcf31655324313dd16df29":4,"61fcf31655324313dd16df2b":4,"61fcf31655324313dd16df2d":4,"61fcf31655324313dd16df2f":4,"61fcf31755324313dd16df31":3,"61fcf31755324313dd16df33":3,"61fcf31755324313dd16df35":4,"61fcf31755324313dd16df37":3,"61fcf31755324313dd16df39":3,"61fcf31755324313dd16df3b":2,"61fcf31755324313dd16df49":3,"61fcf31755324313dd16df4b":3,"61fcf31755324313dd16df4d":4,"61fcf31755324313dd16df4f":4,"61fcf31755324313dd16df51":3,"61fcf31755324313dd16df53":3,"61fcf31755324313dd16df55":3,"61fcf31755324313dd16df57":2,"61fcf31755324313dd16df59":3,"61fcf31755324313dd16df5b":2,"61fcf31755324313dd16df5d":3,"61fcf31755324313dd16df5f":2,"61fcf31755324313dd16df61":3,"61fcf31755324313dd16df63":3,"61fcf31755324313dd16df65":2,"61fcf31755324313dd16df67":2,"61fcf31755324313dd16df69":2,"61fcf31755324313dd16df6b":4,"61fcf31755324313dd16df6d":2,"61fcf31755324313dd16df6f":2,"61fcf31755324313dd16df71":3,"61fcf31755324313dd16df7c":4,"61fcf31755324313dd16df7e":3,"61fcf31755324313dd16df80":3,"61fcf31755324313dd16df82":2,"61fcf31755324313dd16df84":4,"61fcf31755324313dd16df86":3,"61fcf31755324313dd16df97":3,"61fcf31755324313dd16df99":2,"61fcf31755324313dd16dfac":4,"61fcf31755324313dd16dfae":3,"61fcf31755324313dd16dfb0":2,"61fcf31755324313dd16dfb2":3,"61fcf31755324313dd16dfb4":2,"61fcf31755324313dd16dfb6":3,"61fcf31755324313dd16dfb8":2,"61fcf31755324313dd16dfba":2,"61fcf31755324313dd16dfbc":3,"61fcf31755324313dd16dfbe":3,"61fcf31755324313dd16dfc0":2,"61fcf31755324313dd16dfc2":4,"61fcf31755324313dd16dfc4":3,"61fcf31755324313dd16dfc6":3,"61fcf31755324313dd16dfc8":3,"61fcf31755324313dd16dfca":3,"61fcf31755324313dd16dfcc":4,"61fcf31755324313dd16dfce":2,"61fcf31755324313dd16dfd8":2,"61fcf31755324313dd16dfda":3,"61fcf31755324313dd16dfdc":2,"61fcf31755324313dd16dfde":3,"61fcf31755324313dd16dfe0":2,"61fcf31755324313dd16dfe2":3,"61fcf31755324313dd16dfe4":2,"61fcf31755324313dd16dfe6":2,"61fcf31755324313dd16dfe8":2,"61fcf31755324313dd16dfea":2,"61fcf31755324313dd16dfec":1,"61fcf31755324313dd16dfee":4,"61fcf31755324313dd16dff0":2,"61fcf31755324313dd16dff2":2,"61fcf31755324313dd16dff4":3,"61fcf31755324313dd16dff6":3,"61fcf31755324313dd16dff8":3,"61fcf31755324313dd16dffa":2,"61fcf31755324313dd16dffc":4,"61fcf31755324313dd16dffe":2,"61fcf31755324313dd16e000":2,"61fcf31755324313dd16e002":2,"61fcf31755324313dd16e004":3,"61fcf31755324313dd16e006":2,"61fcf31755324313dd16e008":4,"61fcf31755324313dd16e00a":4,"61fcf31755324313dd16e00c":3,"61fcf31755324313dd16e00e":3,"61fcf31755324313dd16e010":4,"61fcf31755324313dd16e012":2,"61fcf31755324313dd16e014":3,"61fcf31755324313dd16e016":2,"61fcf31755324313dd16e018":3,"61fcf31755324313dd16e01a":2,"61fcf31755324313dd16e01c":2,"61fcf31755324313dd16e01e":3,"61fcf31755324313dd16e020":3,"61fcf31755324313dd16e022":3,"61fcf31755324313dd16e024":2,"61fcf31755324313dd16e026":2,"61fcf31755324313dd16e028":1,"61fcf31755324313dd16e02a":1,"61fcf31755324313dd16e032":2,"61fcf31755324313dd16e034":3,"61fcf31755324313dd16e036":1,"61fcf31755324313dd16e038":1,"61fcf31755324313dd16e03a":2,"61fcf31755324313dd16e03c":3,"61fcf31755324313dd16e03e":2,"61fcf31755324313dd16e040":2,"61fcf31755324313dd16e042":4,"61fcf31755324313dd16e044":3,"61fcf31755324313dd16e046":3,"61fcf31755324313dd16e048":2,"61fcf31755324313dd16e04a":4,"61fcf31755324313dd16e04c":3,"61fcf31755324313dd16e04e":1,"61fcf31755324313dd16e058":1,"61fcf31755324313dd16e062":3,"61fcf31755324313dd16e064":3}}}